[
  {
    "filename": "01 Hotel Simon#GG.jpg",
    "caption": "01 Hotel Simon",
    "author": "GG"
  },
  {
    "filename": "02 Hotel Simon reception#GG.jpg",
    "caption": "02 Hotel Simon reception",
    "author": "GG"
  },
  {
    "filename": "03 Hotel Simon first floor#GG.jpg",
    "caption": "03 Hotel Simon first floor",
    "author": "GG"
  },
  {
    "filename": "04 La Giralda bell tower at night#GG.jpg",
    "caption": "04 La Giralda bell tower at night",
    "author": "GG"
  },
  {
    "filename": "05 La Plaza de Espana#GG.jpg",
    "caption": "05 La Plaza de Espana",
    "author": "GG"
  },
  {
    "filename": "06 La Plaza de Espana#GG.jpg",
    "caption": "06 La Plaza de Espana",
    "author": "GG"
  },
  {
    "filename": "07 La Plaza de Espana#GG.jpg",
    "caption": "07 La Plaza de Espana",
    "author": "GG"
  },
  {
    "filename": "08 Catedral de Sevilla#GG.jpg",
    "caption": "08 Catedral de Sevilla",
    "author": "GG"
  },
  {
    "filename": "09 View from the Giralda bell tower#GG.jpg",
    "caption": "09 View from the Giralda bell tower",
    "author": "GG"
  },
  {
    "filename": "10 Catedral de Sevilla#GG.jpg",
    "caption": "10 Catedral de Sevilla",
    "author": "GG"
  },
  {
    "filename": "11 Catedral de Sevilla#GG.jpg",
    "caption": "11 Catedral de Sevilla",
    "author": "GG"
  },
  {
    "filename": "12 Catedral de Sevilla#GG.jpg",
    "caption": "12 Catedral de Sevilla",
    "author": "GG"
  },
  {
    "filename": "13 Iglesia Colegial del Divino Salvador Catholic Church#GG.jpg",
    "caption": "13 Iglesia Colegial del Divino Salvador Catholic Church",
    "author": "GG"
  },
  {
    "filename": "14 Plaza de San Francisco#GG.jpg",
    "caption": "14 Plaza de San Francisco",
    "author": "GG"
  },
  {
    "filename": "15 Casa de Pilatos#GG.jpg",
    "caption": "15 Casa de Pilatos",
    "author": "GG"
  },
  {
    "filename": "16 Casa de Pilatos#GG.jpg",
    "caption": "16 Casa de Pilatos",
    "author": "GG"
  },
  {
    "filename": "17Casa de Pilatos#GG.jpg",
    "caption": "17Casa de Pilatos",
    "author": "GG"
  },
  {
    "filename": "18 Evening at La Plaza de Espana#GG.jpg",
    "caption": "18 Evening at La Plaza de Espana",
    "author": "GG"
  },
  {
    "filename": "19 Photo Shoot at La Plaza de Espana#GG.jpg",
    "caption": "19 Photo Shoot at La Plaza de Espana",
    "author": "GG"
  },
  {
    "filename": "20 Day of the Copa Del Rey#GG.jpg",
    "caption": "20 Day of the Copa Del Rey",
    "author": "GG"
  },
  {
    "filename": "21 Day of the Copa Del Rey#GG.jpg",
    "caption": "21 Day of the Copa Del Rey",
    "author": "GG"
  },
  {
    "filename": "22 Setas de Sevilla#GG.jpg",
    "caption": "22 Setas de Sevilla",
    "author": "GG"
  },
  {
    "filename": "23 Setas de Sevilla#GG.jpg",
    "caption": "23 Setas de Sevilla",
    "author": "GG"
  },
  {
    "filename": "24 Real Alcázar de Sevilla#GG.jpg",
    "caption": "24 Real Alcázar de Sevilla",
    "author": "GG"
  },
  {
    "filename": "25 Real Alcázar de Sevilla#GG.jpg",
    "caption": "25 Real Alcázar de Sevilla",
    "author": "GG"
  },
  {
    "filename": "26 Real Alcázar de Sevilla#GG.jpg",
    "caption": "26 Real Alcázar de Sevilla",
    "author": "GG"
  },
  {
    "filename": "27 Real Alcázar de Sevilla#GG.jpg",
    "caption": "27 Real Alcázar de Sevilla",
    "author": "GG"
  },
  {
    "filename": "28 Museo de las Ilusiones de Sevilla#GG.jpg",
    "caption": "28 Museo de las Ilusiones de Sevilla",
    "author": "GG"
  },
  {
    "filename": "29 Museo de las Ilusiones de Sevilla#GG.jpg",
    "caption": "29 Museo de las Ilusiones de Sevilla",
    "author": "GG"
  },
  {
    "filename": "30 Museo de las Ilusiones de Sevilla#GG.jpg",
    "caption": "30 Museo de las Ilusiones de Sevilla",
    "author": "GG"
  },
  {
    "filename": "31 Museo de las Ilusiones de Sevilla#GG.jpg",
    "caption": "31 Museo de las Ilusiones de Sevilla",
    "author": "GG"
  }
]
